{
  "parent": "minecraft:recipes/root",
  "rewards": {
    "recipes": [
      "contact:light_gray_mailbox"
    ]
  },
  "criteria": {
    "has_dye": {
      "trigger": "minecraft:inventory_changed",
      "conditions": {
        "items": [
          {
            "tag": "forge:dyes/light_gray"
          }
        ]
      }
    },
    "has_the_recipe": {
      "trigger": "minecraft:recipe_unlocked",
      "conditions": {
        "recipe": "contact:light_gray_mailbox"
      }
    }
  },
  "requirements": [
    [
      "has_dye",
      "has_the_recipe"
    ]
  ]
}